odoo8_addon_purchase_commercial_partner-8.0.1.0.0-py2.7-nspkg.pth
odoo_addons/purchase_commercial_partner/__openerp__.py
odoo_addons/purchase_commercial_partner/__init__.py
odoo_addons/purchase_commercial_partner/README.rst
odoo_addons/purchase_commercial_partner/models/purchase.py
odoo_addons/purchase_commercial_partner/models/__init__.py
odoo_addons/purchase_commercial_partner/views/purchase.xml
odoo8_addon_purchase_commercial_partner-8.0.1.0.0.dist-info/top_level.txt
odoo8_addon_purchase_commercial_partner-8.0.1.0.0.dist-info/WHEEL
odoo8_addon_purchase_commercial_partner-8.0.1.0.0.dist-info/RECORD
odoo8_addon_purchase_commercial_partner-8.0.1.0.0.dist-info/metadata.json
odoo8_addon_purchase_commercial_partner-8.0.1.0.0.dist-info/DESCRIPTION.rst
odoo8_addon_purchase_commercial_partner-8.0.1.0.0.dist-info/METADATA
odoo8_addon_purchase_commercial_partner-8.0.1.0.0.dist-info/namespace_packages.txt
